{
	"name": "silver_bja_controles_prenatale",
	"properties": {
		"linkedServiceName": {
			"referenceName": "dw_subsidios",
			"type": "LinkedServiceReference"
		},
		"folder": {
			"name": "Silver/bja"
		},
		"annotations": [],
		"type": "AzureSqlTable",
		"schema": [
			{
				"name": "control_id",
				"type": "int",
				"precision": 10
			},
			{
				"name": "ci_beneficiaria",
				"type": "varchar"
			},
			{
				"name": "establecimiento_id",
				"type": "varchar"
			},
			{
				"name": "nro_control",
				"type": "int",
				"precision": 10
			},
			{
				"name": "fecha_control",
				"type": "date"
			},
			{
				"name": "semana_gestacion",
				"type": "int",
				"precision": 10
			},
			{
				"name": "peso_madre_kg",
				"type": "decimal",
				"precision": 5,
				"scale": 2
			},
			{
				"name": "presion_arterial",
				"type": "varchar"
			}
		],
		"typeProperties": {
			"schema": "silver",
			"table": "bja_controles_prenatales"
		}
	}
}